AUTHORS
ChangeLog
LICENSE
README.rst
bindep.txt
requirements.txt
setup.cfg
setup.py
test-requirements.txt
tox.ini
doc/conf.py
doc/index.rst
logclassify/__init__.py
logclassify/cmd.py
logclassify.egg-info/PKG-INFO
logclassify.egg-info/SOURCES.txt
logclassify.egg-info/dependency_links.txt
logclassify.egg-info/entry_points.txt
logclassify.egg-info/not-zip-safe
logclassify.egg-info/pbr.json
logclassify.egg-info/requires.txt
logclassify.egg-info/top_level.txt