Metadata-Version: 1.1
Name: logclassify
Version: 0.0.0
Summary: extract anomaly from log files
Home-page: https://docs.openstack.org/infra/system-config/
Author: OpenStack Infrastructure Team
Author-email: openstack-infra@lists.openstack.org
License: UNKNOWN
Keywords: machine learning,ci,anomaly detection
Platform: UNKNOWN
Classifier: Intended Audience :: Information Technology
Classifier: Intended Audience :: System Administrators
Classifier: License :: OSI Approved :: Apache Software License
Classifier: Programming Language :: Python
Classifier: Programming Language :: Python :: 3.5
